gemini_live_voice_only/__init__.py
gemini_live_voice_only/gemini_handler.py
gemini_live_voice_only/stream_server.py
gemini_live_voice_only-0.1.1.dist-info/LICENSE.txt
gemini_live_voice_only-0.1.1.dist-info/METADATA
gemini_live_voice_only-0.1.1.dist-info/WHEEL
gemini_live_voice_only-0.1.1.dist-info/top_level.txt
gemini_live_voice_only-0.1.1.dist-info/RECORD
