Metadata-Version: 2.2
Name: gemini_live_voice_only
Version: 0.1.1
Summary: A real-time Gemini API streaming library with FastAPI integration
Author: Omanand Swami
Author-email: omanandswami2005@gmail.com
Classifier: Programming Language :: Python :: 3
Classifier: Operating System :: OS Independent
Requires: python (>=3.12)
License-File: LICENSE.txt
Requires-Dist: fastapi
Requires-Dist: uvicorn
Requires-Dist: numpy
Requires-Dist: python-dotenv
Requires-Dist: fastrtc
Requires-Dist: google-genai
Dynamic: author
Dynamic: author-email
Dynamic: classifier
Dynamic: description
Dynamic: description-content-type
Dynamic: requires
Dynamic: requires-dist
Dynamic: summary
